flask_sparkle/__init__.py
flask_sparkle/admin.py
flask_sparkle/documents.py
flask_sparkle/resources.py
flask_sparkle/schemas.py
flask_sparkle/views.py
flask_sparkle/templates/appcast.xml
flask_sparkle-0.3.0.dist-info/DESCRIPTION.rst
flask_sparkle-0.3.0.dist-info/METADATA
flask_sparkle-0.3.0.dist-info/RECORD
flask_sparkle-0.3.0.dist-info/WHEEL
flask_sparkle-0.3.0.dist-info/metadata.json
flask_sparkle-0.3.0.dist-info/top_level.txt
