Metadata-Version: 2.0
Name: flask-sparkle
Version: 0.3.0
Summary: Flask app that publishes Sparkle update feeds
Home-page: http://github.com/closeio/flask-sparkle
Author: Close.io
Author-email: engineering@close.io
Maintainer: Close.io
Maintainer-email: engineering@close.io
License: MIT
Platform: any
Classifier: Intended Audience :: Developers
Classifier: Operating System :: OS Independent
Classifier: Topic :: Software Development :: Libraries :: Python Modules
Classifier: Programming Language :: Python
Classifier: Programming Language :: Python :: 2
